MANIFEST.in
README
setup.cfg
setup.py
Plurk_Solace.egg-info/PKG-INFO
Plurk_Solace.egg-info/SOURCES.txt
Plurk_Solace.egg-info/dependency_links.txt
Plurk_Solace.egg-info/not-zip-safe
Plurk_Solace.egg-info/requires.txt
Plurk_Solace.egg-info/top_level.txt
solace/__init__.py
solace/application.py
solace/auth.py
solace/badges.py
solace/database.py
solace/forms.py
solace/models.py
solace/packs.py
solace/scripts.py
solace/settings.py
solace/templating.py
solace/urls.py
solace/i18n/__init__.py
solace/static/arrows.png
solace/static/arrows_gray.png
solace/static/babel.js
solace/static/badge_earned.png
solace/static/badge_not_earned.png
solace/static/badges.css
solace/static/creole.js
solace/static/feed.png
solace/static/flashtick.png
solace/static/ie.css
solace/static/ie6.css
solace/static/jquery.autocomplete.js
solace/static/jquery.form.js
solace/static/jquery.js
solace/static/layout.css
solace/static/recycle.png
solace/static/recycle_big.png
solace/static/solace.js
solace/static/teal.css
solace/static/tick.png
solace/static/tick_gray.png
solace/static/badges/critic.png
solace/static/badges/editor.png
solace/static/badges/good_answer.png
solace/static/badges/great_answer.png
solace/static/badges/inquirer.png
solace/static/badges/nice_answer.png
solace/static/badges/reversal.png
solace/static/badges/self_critic.png
solace/static/badges/self_learner.png
solace/static/badges/troubleshooter.png
solace/static/badges/unique_answer.png
solace/templates/_helpers.html
solace/templates/layout.html
solace/templates/api/debug_dump.html
solace/templates/api/help.html
solace/templates/badges/show_badge.html
solace/templates/badges/show_list.html
solace/templates/core/about.html
solace/templates/core/login.html
solace/templates/core/no_javascript.html
solace/templates/core/not_found.html
solace/templates/core/register.html
solace/templates/core/reset_password.html
solace/templates/kb/_boxes.html
solace/templates/kb/_comments.html
solace/templates/kb/_editor.html
solace/templates/kb/by_tag.html
solace/templates/kb/delete_post.html
solace/templates/kb/edit_post.html
solace/templates/kb/new.html
solace/templates/kb/overview.html
solace/templates/kb/post_revisions.html
