Metadata-Version: 1.0
Name: Plurk-Solace
Version: 0.1
Summary: Multilangual User Support Platform
Home-page: http://opensource.plurk.com/solace/
Author: Plurk Inc.
Author-email: opensource@plurk.com
License: BSD
Platform: any
